jupytercad/__init__.py
jupytercad-3.4.0.dist-info/METADATA
jupytercad-3.4.0.dist-info/WHEEL
jupytercad-3.4.0.dist-info/licenses/LICENSE
jupytercad-3.4.0.dist-info/RECORD
