Metadata-Version: 2.4
Name: jupytercad
Version: 3.4.0
License: BSD 3-Clause License
License-File: LICENSE
Classifier: Framework :: Jupyter
Classifier: Framework :: Jupyter :: JupyterLab
Classifier: Framework :: Jupyter :: JupyterLab :: 4
Classifier: Framework :: Jupyter :: JupyterLab :: Extensions
Classifier: Framework :: Jupyter :: JupyterLab :: Extensions :: Prebuilt
Classifier: License :: OSI Approved :: BSD License
Classifier: Programming Language :: Python
Classifier: Programming Language :: Python :: 3
Classifier: Programming Language :: Python :: 3.8
Classifier: Programming Language :: Python :: 3.9
Classifier: Programming Language :: Python :: 3.10
Classifier: Programming Language :: Python :: 3.11
Classifier: Programming Language :: Python :: 3.12
Classifier: Programming Language :: Python :: 3.13
Classifier: Programming Language :: Python :: 3.14
Requires-Python: >=3.8
Requires-Dist: jupyter-collaboration-ui<3,>=2
Requires-Dist: jupyter-collaboration<5,>=4
Requires-Dist: jupyter-docprovider<3,>=2
Requires-Dist: jupyter-server-ydoc<3,>=2
Requires-Dist: jupytercad-app==3.4.0
Requires-Dist: jupytercad-core==3.4.0
Requires-Dist: jupytercad-lab==3.4.0
Requires-Dist: jupyterlab<5,>=4.5.1
